Workbook

Sheet Financial Analysis
A1: Financial Analysis
B2: Main Sheet
A4: Year | D4: 1 | E4: 2 | F4: 3 | G4: 4 | H4: 5 | I4: 6 | J4: 7 | K4: 8 | L4: 9 | M4: 10 | N4: 11 | O4: 12 | P4: 13 | Q4: 14 | R4: 15 | S4: 16 | T4: 17 | U4: 18 | V4: 19 | W4: 20 | X4: 21 | Y4: 22 | Z4: 23 | AA4: 24 | AB4: 25 | AC4: 26
A5: Year March Ending | D5: 2025-26 | E5: 2026-27 | F5: 2027-28 | G5: 2028-29 | H5: 2029-30 | I5: 2030-31 | J5: 2031-32 | K5: 2032-33 | L5: 2033-34 | M5: 2034-35 | N5: 2035-36 | O5: 2036-37 | P5: 2037-38 | Q5: 2038-39 | R5: 2039-40 | S5: 2040-41 | T5: 2041-42 | U5: 2042-43 | V5: 2043-44 | W5: 2044-45 | X5: 2045-46 | Y5: 2046-47 | Z5: 2047-48 | AA5: 2048-49 | AB5: 2038-39 | AC5: 2040-41
A7: DSCR Calculation | B7: Cash accrual (PAT+Dep+Interest) | D7: =D15+D16+D17 | E7: =E15+E16+E17 | F7: =F15+F16+F17 | G7: =G15+G16+G17 | H7: =H15+H16+H17 | I7: =I15+I16+I17 | J7: =J15+J16+J17 | K7: =K15+K16+K17 | ... AC7: =AC15+AC16+AC17
B8: Debt repayment (Interest + Principal) | D8: 35.75 | E8: 94.36 | F8: 90.78 | G8: 87.21 | H8: 83.63 | I8: 80.06 | J8: 76.48 | K8: 72.9 | L8: 69.33 | M8: 65.75 | N8: 62.18 | O8: 0 | P8: 0 | Q8: 0 | R8: 0 | S8: 0 | T8: 0 | U8: 0 | V8: 0 | W8: 0 | X8: 0 | Y8: 0 | Z8: 0 | AA8: 0 | AB8: 0 | AC8: 0
B9: DSCR | D9: =IF(D8=0, 0.00, D7/D8) | E9: =IF(E8=0, 0.00, E7/E8) | F9: =IF(F8=0, 0.00, F7/F8) | G9: =IF(G8=0, 0.00, G7/G8) | H9: =IF(H8=0, 0.00, H7/H8) | I9: =IF(I8=0, 0.00, I7/I8) | J9: =IF(J8=0, 0.00, J7/J8) | K9: =IF(K8=0, 0.00, K7/K8) | ... AC9: =IF(AC8=0, 0.00, AC7/AC8)
B10: MIN DSCR | C10: =MIN(D9:N9)
B11: Average DSCR | C11: =AVERAGE(D9:N9)
B12: MAX DSCR | C12: =MAX(D9:N9)
A14: Project IRR | B14: Capital Expenditure | C14: -788.72
B15: PAT | D15: 24.09 | E15: 49.54 | F15: 41.3 | G15: 43.58 | H15: 45.62 | I15: 47.84 | J15: 50.02 | K15: 52.18 | L15: 54.3 | M15: 56.38 | N15: 58.43 | O15: 60.44 | P15: 62.41 | Q15: 64.33 | R15: 66.22 | S15: 68.05 | T15: 68.77 | U15: 67.67 | V15: 61.53 | W15: 60.4 | X15: 59.21 | Y15: 57.96 | Z15: 56.65 | AA15: 55.27 | AB15: 73.77 | AC15: 73.77
B16: Depreciation | D16: =Depreciation!D11 | E16: =Depreciation!E11 | F16: =Depreciation!F11 | G16: =Depreciation!G11 | H16: =Depreciation!H11 | I16: =Depreciation!I11 | J16: =Depreciation!J11 | K16: =Depreciation!K11 | ... AC16: =Depreciation!AC11
B17: Interest | D17: 26.82 | E17: 52.29 | F17: 48.72 | G17: 45.14 | H17: 41.57 | I17: 37.99 | J17: 34.41 | K17: 30.84 | L17: 27.26 | M17: 23.69 | N17: 20.11 | O17: 16.54 | P17: 12.96 | Q17: 9.39 | R17: 5.8 | S17: 2.22 | T17: 0 | U17: 0 | V17: 0 | W17: 0 | X17: 0 | Y17: 0 | Z17: 0 | AA17: 0 | AB17: 0 | AC17: 0
B18: Salvage Value | D18: 0 | E18: 0 | F18: 0 | G18: 0 | H18: 0 | I18: 0 | J18: 0 | K18: 0 | L18: 0 | M18: 0 | N18: 0 | O18: 0 | P18: 0 | Q18: 0 | R18: 0 | S18: 0 | T18: 0 | U18: 0 | V18: 0 | W18: 0 | X18: 0 | Y18: 0 | Z18: 0 | AA18: 0 | AB18: 0 | AC18: 78.87
B19: Incremental Margin Money for WC | D19: 2.41 | E19: 2.4 | F19: 0.58 | G19: 0.03 | H19: 0.02 | I19: 0.03 | J19: 0.03 | K19: 0.04 | L19: 0.04 | M19: 0.04 | N19: 0.04 | O19: 0.04 | P19: 0.05 | Q19: 0.05 | R19: 0.05 | S19: 0.05 | T19: 0.05 | U19: 0.05 | V19: 0.05 | W19: 0.06 | X19: 0.07 | Y19: 0.07 | Z19: 0.08 | AA19: 0 | AB19: 0 | AC19: 0
B20: Net Cash Flow | C20: 0 | D20: =D14+D15+D16+D17+D18-D19+C14 | E20: =E14+E15+E16+E17+E18-E19 | F20: =F14+F15+F16+F17+F18-F19 | G20: =G14+G15+G16+G17+G18-G19 | H20: =H14+H15+H16+H17+H18-H19 | I20: =I14+I15+I16+I17+I18-I19 | J20: =J14+J15+J16+J17+J18-J19 | K20: =K14+K15+K16+K17+K18-K19 | L20: =L14+L15+L16+L17+L18-L19 | ... AC20: =AC14+AC15+AC16+AC17+AC18-AC19
B21: Project IRR | C21: =IRR(D20:AC20)
A24: Equity IRR | B24: Equity Investment | C24: -157.74
B25: PAT | D25: =D15 | E25: =E15 | F25: =F15 | G25: =G15 | H25: =H15 | I25: =I15 | J25: =J15 | K25: =K15 | ... AC25: =AC15
B26: Depreciation | D26: =D16 | E26: =E16 | F26: =F16 | G26: =G16 | H26: =H16 | I26: =I16 | J26: =J16 | K26: =K16 | ... AC26: =AC16
B27: Salvage Value | D27: 0 | E27: 0 | F27: 0 | G27: 0 | H27: 0 | I27: 0 | J27: 0 | K27: 0 | L27: 0 | M27: 0 | N27: 0 | O27: 0 | P27: 0 | Q27: 0 | R27: 0 | S27: 0 | T27: 0 | U27: 0 | V27: 0 | W27: 0 | X27: 0 | Y27: 0 | Z27: 0 | AA27: 0 | AB27: 0 | AC27: 78.87
B28: Less Repayment of Term Loan | D28: 0 | E28: 42.07 | F28: 42.07 | G28: 42.07 | H28: 42.07 | I28: 42.07 | J28: 42.07 | K28: 42.07 | L28: 42.07 | M28: 42.07 | N28: 42.07 | O28: 42.07 | P28: 42.07 | Q28: 42.07 | R28: 42.07 | S28: 42.07 | T28: 0 | U28: 0 | V28: 0 | W28: 0 | X28: 0 | Y28: 0 | Z28: 0 | AA28: 0 | AB28: 0 | AC28: 0
B29: Net Cash Flow | D29: =D25+D26+D27-D28+C24 | E29: =E25+E26+E27-E28 | F29: =F25+F26+F27-F28 | G29: =G25+G26+G27-G28 | H29: =H25+H26+H27-H28 | I29: =I25+I26+I27-I28 | J29: =J25+J26+J27-J28 | K29: =K25+K26+K27-K28 | L29: =L25+L26+L27-L28 | ... AC29: =AC25+AC26+AC27-AC28
B30: Equity IRR | C30: =IRR(D29:AC29)

Sheet Depreciation
A1: Depreciation
A2: (Figures in Rs. Crores) | B2: Main Sheet
A3: Year | D3: 1 | E3: 2 | F3: 3 | G3: 4 | H3: 5 | I3: 6 | J3: 7 | K3: 8 | L3: 9 | M3: 10 | N3: 11 | O3: 12 | P3: 13 | Q3: 14 | R3: 15 | S3: 16 | T3: 17 | U3: 18 | V3: 19 | W3: 20 | X3: 21 | Y3: 22 | Z3: 23 | AA3: 24 | AB3: 25 | AC3: 26
A4: FY | D4: 2025-26 | E4: 2026-27 | F4: 2027-28 | G4: 2028-29 | H4: 2029-30 | I4: 2030-31 | J4: 2031-32 | K4: 2032-33 | L4: 2033-34 | M4: 2034-35 | N4: 2035-36 | O4: 2036-37 | P4: 2037-38 | Q4: 2038-39 | R4: 2039-40 | S4: 2040-41 | T4: 2041-42 | U4: 2042-43 | V4: 2043-44 | W4: 2044-45 | X4: 2045-46 | Y4: 2046-47 | Z4: 2047-48 | AA4: 2048-49 | AB4: 2038-39 | AC4: 2040-41
A6: Total depreciable cost | C6: =C30
A7: Depreciable Life | B7: 25 | C7: Years
A8: Salvage Value | B8: 0.1
A10: After 10 years, balance asset value equally spread
A11: Depreciation in Books | D11: =ROUND((C28*0.02 + C29*0.08)*1/12, 2) | E11: =ROUND(($C$28*0.02 + $C$29*0.08), 2) | F11: =ROUND(($C$28*0.02 + $C$29*0.08), 2) | G11: =ROUND(($C$28*0.02 + $C$29*0.08), 2) | H11: =ROUND(($C$28*0.02 + $C$29*0.08), 2) | I11: =ROUND(($C$28*0.02 + $C$29*0.08), 2) | J11: =ROUND(($C$28*0.02 + $C$29*0.08), 2) | K11: =ROUND(($C$28*0.02 + $C$29*0.08), 2) | L11: =ROUND(($C$28*0.02 + $C$29*0.08), 2) | M11: =ROUND(($C$28*0.02 + $C$29*0.08), 2) | N11: =ROUND(($C$6 - SUM($D$11:$M$11))/15, 2) | O11: =ROUND(($C$6 - SUM($D$11:$M$11))/15, 2) | P11: =ROUND(($C$6 - SUM($D$11:$M$11))/15, 2) | Q11: =ROUND(($C$6 - SUM($D$11:$M$11))/15, 2) | R11: =ROUND(($C$6 - SUM($D$11:$M$11))/15, 2) | S11: =ROUND(($C$6 - SUM($D$11:$M$11))/15, 2) | T11: =ROUND(($C$6 - SUM($D$11:$M$11))/15, 2) | U11: =ROUND(($C$6 - SUM($D$11:$M$11))/15, 2) | ... AC11: =ROUND(($C$6 - SUM($D$11:$M$11))/15, 2)
A13: As Per Income Tax - WDV
A15: Civil Works | C15: 0.1
B16: Opening Value | D16: =C28 | E16: =D18 | F16: =E18 | G16: =F18 | H16: =G18 | I16: =H18 | J16: =I18 | K16: =J18 | L16: =K18 | ... AC16: =AB18
B17: Depreciation | D17: =ROUND(D16 * $C$15 * 9/12, 2) | E17: =ROUND(E16 * $C$15, 2) | F17: =ROUND(F16 * $C$15, 2) | G17: =ROUND(G16 * $C$15, 2) | H17: =ROUND(H16 * $C$15, 2) | I17: =ROUND(I16 * $C$15, 2) | J17: =ROUND(J16 * $C$15, 2) | K17: =ROUND(K16 * $C$15, 2) | L17: =ROUND(L16 * $C$15, 2) | ... AC17: =ROUND(AC16 * $C$15, 2)
B18: Closing Value | D18: =ROUND(D16 - D17, 2) | E18: =ROUND(E16 - E17, 2) | F18: 1.02 | G18: =ROUND(G16 - G17, 2) | H18: =ROUND(H16 - H17, 2) | I18: =ROUND(I16 - I17, 2) | J18: =ROUND(J16 - J17, 2) | K18: =ROUND(K16 - K17, 2) | L18: =ROUND(L16 - L17, 2) | M18: =ROUND(M16 - M17, 2) | N18: =ROUND(N16 - N17, 2) | ... AC18: =ROUND(AC16 - AC17, 2)
A20: Plant & Machinery | C20: 0.15
B21: Opening Value | D21: =C29 | E21: =D23 | F21: =E23 | G21: =F23 | H21: =G23 | I21: =H23 | J21: =I23 | K21: =J23 | L21: =K23 | ... AC21: =AB23
B22: Depreciation | D22: =ROUND(D21 * $C$20 * 9/12, 2) | E22: =ROUND(E21 * $C$20, 2) | F22: 0.2 | G22: =ROUND(G21 * $C$20, 2) | H22: =ROUND(H21 * $C$20, 2) | I22: =ROUND(I21 * $C$20, 2) | J22: =ROUND(J21 * $C$20, 2) | K22: =ROUND(K21 * $C$20, 2) | L22: =ROUND(L21 * $C$20, 2) | M22: =ROUND(M21 * $C$20, 2) | N22: =ROUND(N21 * $C$20, 2) | ... AC22: =ROUND(AC21 * $C$20, 2)
B23: Closing Value | D23: =ROUND(D21 - D22, 2) | E23: =ROUND(E21 - E22, 2) | F23: =ROUND(F21 - F22, 2) | G23: =ROUND(G21 - G22, 2) | H23: =ROUND(H21 - H22, 2) | I23: =ROUND(I21 - I22, 2) | J23: =ROUND(J21 - J22, 2) | K23: =ROUND(K21 - K22, 2) | ... AC23: =ROUND(AC21 - AC22, 2)
A25: Total IT Depreciation | D25: =D17+D22 | E25: =E17+E22 | F25: =F17+F22 | G25: =G17+G22 | H25: =H17+H22 | I25: =I17+I22 | J25: =J17+J22 | K25: =K17+K22 | ... AC25: =AC17+AC22
A27: Component | C27: Capitalized Amount in Rs.
A28: Civil Works | C28: 1.37
A29: Plant & Machinery | C29: 7
A30: Depreciable Base | C30: =SUM(C28:C29)
A31: Weighted Average Rate of Depreciation | C31: =ROUND((C28*C15+C29*C20)/C30, 4)
A33: Depreciation Rates as per Income Tax
A34: Under IT Act (WDV) - Equipment | C34: 0.15
A35: Under IT Act (WDV) - Buildings | C35: 0.1
